polynom/__init__.py
polynom/application.py
polynom/config.py
polynom/docker.py
polynom/dump.py
polynom/joined_load.py
polynom/query.py
polynom/reflection.py
polynom/session.py
polynom/statement.py
polynom/statement_logger.py
polynom/model/__init__.py
polynom/model/model.py
polynom/model/model_registry.py
polynom/model/relationship.py
polynom/schema/__init__.py
polynom/schema/cascade.py
polynom/schema/field.py
polynom/schema/migration.py
polynom/schema/polytypes.py
polynom/schema/schema.py
polynom/schema/schema_registry.py
polypheny_polynom-0.3.2.dist-info/licenses/LICENSE
polypheny_polynom-0.3.2.dist-info/METADATA
polypheny_polynom-0.3.2.dist-info/WHEEL
polypheny_polynom-0.3.2.dist-info/top_level.txt
polypheny_polynom-0.3.2.dist-info/RECORD
