Metadata-Version: 2.4
Name: polypheny-polynom
Version: 0.3.2
Summary: Object Mapper for Polypheny
Home-page: https://polypheny.com/
Author: The Polypheny Project
Author-email: mail@polypheny.org
License: Apache License, Version 2.0
Project-URL: Documentation, https://github.com/polypheny/PolyNOM/docs
Project-URL: Code, https://github.com/polypheny/PolyNOM
Requires-Python: >=3.11
License-File: LICENSE
Requires-Dist: polypheny
Requires-Dist: docker
Requires-Dist: shapely
Provides-Extra: dev
Requires-Dist: pytest; extra == "dev"
Dynamic: author
Dynamic: author-email
Dynamic: description
Dynamic: description-content-type
Dynamic: home-page
Dynamic: license
Dynamic: license-file
Dynamic: project-url
Dynamic: provides-extra
Dynamic: requires-dist
Dynamic: requires-python
Dynamic: summary
